[{"name":"t1","properties":"({     name : \"t1\",     p1 : \"\",     p2 : \"\",  p3:\"\",     constructor : function(message){         this.p1 = message;     } })"},{"name":"t2","properties":"({     name : \"t2\",     p1 : \"\",     p2 : \"\",  p3:\"\",   constructor : function(message1, message2){         this.p1 = message1;         this.p2 = message2;     } })"},{"name":"t3","properties":"({     name : \"t3\",     p1 : \"\",     p2 : \"\",  p3:\"\",     constructor : function(message){         this.p1 = message;    } })"},{"name":"t4","properties":"({     name : \"t4\",     p1 : \"\",     p2 : \"\",  p3:\"\",     constructor : function(message1, message2){         this.p1 = message1;         this.p2 = message2;  } })"},{"name":"l51","properties":"({     name : \"l1\",     p1 : \"\",     p2 : \"\",     constructor : function(message1, message2){         this.p1 = message1;         this.p2 = message2;  } })"},{"name":"l52","properties":"({     name : \"l2\",     p1 : \"\",     p2 : \"\",     constructor : function(message1, message2){         this.p1 = message1;         this.p2 = message2;  } })"},{"name":"l196","properties":"({     name : \"l196\",     p1 : \"\",     p2 : \"\",     constructor : function(message1, message2){         this.p1 = message1;         this.p2 = message2;  } })"},{"name":"l197","properties":"({     name : \"l197\",     p1 : \"\",     p2 : \"\",     constructor : function(message1, message2){         this.p1 = message1;         this.p2 = message2;  } })"},{"name":"weather","properties":"({     name : \"weather\",     pweather_today : \"\",     ptemperature_today: \"\",     phumidity_today: \"\",     pfineDust_today: \"\",     pultrafineDust_today: \"\",     pweather_tomorrow: \"\",     ptemperature_tomorrow: \"\",     ptemperature_today: \"\",     phumidity_tomorrow: \"\",     pfineDust_tomorrow: \"\",pultrafineDust_tomorrow: \"\",constructor: function(message){this.pweather_today=message.weather_today;this.ptemperature_today=message.temperature_today;this.phumidity_today=message.humidity_today;this.pfineDust_today=message.fineDust_today;this.pultrafineDust_today=message.ultrafineDust_today;this.pweather_tomorrow=message.weather_tomorrow;this.ptemperature_tomorrow=message.temperature_tomorrow;this.phumidity_tomorrow=message.humidity_tomorrow;this.pfineDust_tomorrow=message.fineDust_tomorrow;this.pultrafineDust_tomorrow=message.ultrafineDust_tomorrow;} })"},{"name":"t130","properties":"({name : 't130',     p1 : '',p2 : '',p3 : '',     text2 : '',constructor : function(message){         this.p1=message.ThingData.Part1; this.p2=message.ThingData.Part2;  this.p1=message.ThingData.Part1;}, })"},{"name":"t131","properties":"({name : 't131',     p1 : '',p2 : '',p3 : '',     text2 : '',constructor : function(message){         this.p1=message.ThingData.Part1; this.p2=message.ThingData.Part2;  this.p1=message.ThingData.Part1;}, })"},{"name":"t132","properties":"({name : 't132',     p1 : '',p2 : '',p3 : '',     text2 : '',constructor : function(message){         this.p1=message.ThingData.Part1; this.p2=message.ThingData.Part2;  this.p1=message.ThingData.Part1;}, })"},{"name":"t133","properties":"({name : 't133',     p1 : '',p2 : '',p3 : '',     text2 : '',constructor : function(message){         this.p1=message.ThingData.Part1; this.p2=message.ThingData.Part2;  this.p1=message.ThingData.Part1;}, })"},{"name":"t134","properties":"({name : 't134',     p1 : '',p2 : '',p3 : '',     text2 : '',constructor : function(message){         this.p1=message.ThingData.Part1; this.p2=message.ThingData.Part2;  this.p1=message.ThingData.Part1;}, })"},{"name":"t95","properties":"({name : 't95',     p1 : '',p2 : '',p3 : '',     text2 : '',constructor : function(message){         this.p1=message.ThingData.Part1; this.p2=message.ThingData.Part2;  this.p1=message.ThingData.Part1;}, })"},{"name":"t97","properties":"({name : 't97',     p1 : '',p2 : '',p3 : '',     text2 : '',constructor : function(message){         this.p1=message.ThingData.Part1; this.p2=message.ThingData.Part2;  this.p1=message.ThingData.Part1;}, })"},{"name":"t98","properties":"({name : 't98',     p1 : '',p2 : '',p3 : '',     text2 : '',constructor : function(message){         this.p1=message.ThingData.Part1; this.p2=message.ThingData.Part2;  this.p1=message.ThingData.Part1;}, })"},{"name":"t99","properties":"({name : 't99',     p1 : '',p2 : '',p3 : '',     text2 : '',constructor : function(message){         this.p1=message.ThingData.Part1; this.p2=message.ThingData.Part2;  this.p1=message.ThingData.Part1;}, })"},{"name":"t100","properties":"({name : 't100',     p1 : '',p2 : '',p3 : '',     text2 : '',constructor : function(message){         this.p1=message.ThingData.Part1; this.p2=message.ThingData.Part2;  this.p1=message.ThingData.Part1;}, })"},{"name":"t101","properties":"({name : 't101',     p1 : '',p2 : '',p3 : '',     text2 : '',constructor : function(message){         this.p1=message.ThingData.Part1; this.p2=message.ThingData.Part2;  this.p1=message.ThingData.Part1;}, })"},{"name":"t102","properties":"({name : 't102',     p1 : '',p2 : '',p3 : '',     text2 : '',constructor : function(message){         this.p1=message.ThingData.Part1; this.p2=message.ThingData.Part2;  this.p1=message.ThingData.Part1;}, })"},{"name":"t103","properties":"({name : 't103',     p1 : '',p2 : '',p3 : '',     text2 : '',constructor : function(message){         this.p1=message.ThingData.Part1; this.p2=message.ThingData.Part2;  this.p1=message.ThingData.Part1;}, })"},{"name":"t104","properties":"({name : 't104',     p1 : '',p2 : '',p3 : '',     text2 : '',constructor : function(message){         this.p1=message.ThingData.Part1; this.p2=message.ThingData.Part2;  this.p1=message.ThingData.Part1;}, })"},{"name":"t105","properties":"({name : 't105',     p1 : '',p2 : '',p3 : '',     text2 : '',constructor : function(message){         this.p1=message.ThingData.Part1; this.p2=message.ThingData.Part2;  this.p1=message.ThingData.Part1;}, })"},{"name":"t106","properties":"({name : 't106',     p1 : '',p2 : '',p3 : '',     text2 : '',constructor : function(message){         this.p1=message.ThingData.Part1; this.p2=message.ThingData.Part2;  this.p1=message.ThingData.Part1;}, })"},{"name":"t107","properties":"({name : 't107',     p1 : '',p2 : '',p3 : '',     text2 : '',constructor : function(message){         this.p1=message.ThingData.Part1; this.p2=message.ThingData.Part2;  this.p1=message.ThingData.Part1;}, })"},{"name":"t108","properties":"({name : 't108',     p1 : '',p2 : '',p3 : '',     text2 : '',constructor : function(message){         this.p1=message.ThingData.Part1; this.p2=message.ThingData.Part2;  this.p1=message.ThingData.Part1;}, })"},{"name":"t109","properties":"({name : 't109',     p1 : '',p2 : '',p3 : '',     text2 : '',constructor : function(message){         this.p1=message.ThingData.Part1; this.p2=message.ThingData.Part2;  this.p1=message.ThingData.Part1;}, })"},{"name":"t110","properties":"({name : 't110',     p1 : '',p2 : '',p3 : '',     text2 : '',constructor : function(message){         this.p1=message.ThingData.Part1; this.p2=message.ThingData.Part2;  this.p1=message.ThingData.Part1;}, })"},{"name":"t111","properties":"({name : 't111',     p1 : '',p2 : '',p3 : '',     text2 : '',constructor : function(message){         this.p1=message.ThingData.Part1; this.p2=message.ThingData.Part2;  this.p1=message.ThingData.Part1;}, })"},{"name":"t112","properties":"({name : 't112',     p1 : '',p2 : '',p3 : '',     text2 : '',constructor : function(message){         this.p1=message.ThingData.Part1; this.p2=message.ThingData.Part2;  this.p1=message.ThingData.Part1;}, })"},{"name":"t113","properties":"({name : 't113',     p1 : '',p2 : '',p3 : '',     text2 : '',constructor : function(message){         this.p1=message.ThingData.Part1; this.p2=message.ThingData.Part2;  this.p1=message.ThingData.Part1;}, })"},{"name":"t114","properties":"({name : 't114',     p1 : '',p2 : '',p3 : '',     text2 : '',constructor : function(message){         this.p1=message.ThingData.Part1; this.p2=message.ThingData.Part2;  this.p1=message.ThingData.Part1;}, })"},{"name":"t115","properties":"({name : 't115',     p1 : '',p2 : '',p3 : '',     text2 : '',constructor : function(message){         this.p1=message.ThingData.Part1; this.p2=message.ThingData.Part2;  this.p1=message.ThingData.Part1;}, })"},{"name":"t116","properties":"({name : 't116',     p1 : '',p2 : '',p3 : '',     text2 : '',constructor : function(message){         this.p1=message.ThingData.Part1; this.p2=message.ThingData.Part2;  this.p1=message.ThingData.Part1;}, })"},{"name":"t117","properties":"({name : 't117',     p1 : '',p2 : '',p3 : '',     text2 : '',constructor : function(message){         this.p1=message.ThingData.Part1; this.p2=message.ThingData.Part2;  this.p1=message.ThingData.Part1;}, })"},{"name":"t118","properties":"({name : 't118',     p1 : '',p2 : '',p3 : '',     text2 : '',constructor : function(message){         this.p1=message.ThingData.Part1; this.p2=message.ThingData.Part2;  this.p1=message.ThingData.Part1;}, })"},{"name":"t119","properties":"({name : 't119',     p1 : '',p2 : '',p3 : '',     text2 : '',constructor : function(message){         this.p1=message.ThingData.Part1; this.p2=message.ThingData.Part2;  this.p1=message.ThingData.Part1;}, })"},{"name":"t120","properties":"({name : 't120',     p1 : '',p2 : '',p3 : '',     text2 : '',constructor : function(message){         this.p1=message.ThingData.Part1; this.p2=message.ThingData.Part2;  this.p1=message.ThingData.Part1;}, })"},{"name":"t121","properties":"({name : 't121',     p1 : '',p2 : '',p3 : '',     text2 : '',constructor : function(message){         this.p1=message.ThingData.Part1; this.p2=message.ThingData.Part2;  this.p1=message.ThingData.Part1;}, })"},{"name":"t122","properties":"({name : 't122',     p1 : '',p2 : '',p3 : '',     text2 : '',constructor : function(message){         this.p1=message.ThingData.Part1; this.p2=message.ThingData.Part2;  this.p1=message.ThingData.Part1;}, })"},{"name":"t123","properties":"({name : 't123',     p1 : '',p2 : '',p3 : '',     text2 : '',constructor : function(message){         this.p1=message.ThingData.Part1; this.p2=message.ThingData.Part2;  this.p1=message.ThingData.Part1;}, })"},{"name":"t124","properties":"({name : 't124',     p1 : '',p2 : '',p3 : '',     text2 : '',constructor : function(message){         this.p1=message.ThingData.Part1; this.p2=message.ThingData.Part2;  this.p1=message.ThingData.Part1;}, })"}]